littlefscli/__init__.py
littlefscli/config.ini
littlefscli/enable_littlefs.py
littlefscli/templates/task.partition.template.json
littlefscli/templates/tasks.base.template.json
enable_littlefs-1.0.2.dist-info/LICENSE
enable_littlefs-1.0.2.dist-info/METADATA
enable_littlefs-1.0.2.dist-info/WHEEL
enable_littlefs-1.0.2.dist-info/entry_points.txt
enable_littlefs-1.0.2.dist-info/top_level.txt
enable_littlefs-1.0.2.dist-info/RECORD
