Metadata-Version: 2.1
Name: enable-littlefs
Version: 1.0.2
Summary: ESP-IDF utility for generating VSCode tasks and LittleFS support
Author: PoleG97
Classifier: Programming Language :: Python :: 3
Classifier: Operating System :: OS Independent
Requires-Python: >=3.6
License-File: LICENSE
